bigquery_helper/__init__.py
bigquery_helper/helper.py
bigquery_helper-0.1.0.dist-info/LICENSE
bigquery_helper-0.1.0.dist-info/METADATA
bigquery_helper-0.1.0.dist-info/WHEEL
bigquery_helper-0.1.0.dist-info/top_level.txt
bigquery_helper-0.1.0.dist-info/RECORD
