Metadata-Version: 2.1
Name: bigquery-helper
Version: 0.1.0
Summary: A helper package for Google BigQuery operations
Home-page: https://github.com/memsjava/bigquery-helper
Author: Rabemampiandra
Author-email: memsjava@gmail.com
Classifier: Development Status :: 3 - Alpha
Classifier: Intended Audience :: Developers
Classifier: License :: OSI Approved :: MIT License
Classifier: Operating System :: OS Independent
Classifier: Programming Language :: Python :: 3
Classifier: Programming Language :: Python :: 3.7
Classifier: Programming Language :: Python :: 3.8
Classifier: Programming Language :: Python :: 3.9
Requires-Python: >=3.7
License-File: LICENSE
Requires-Dist: google-cloud-bigquery (>=3.0.0)
Requires-Dist: pandas (>=1.0.0)
Requires-Dist: pandas-gbq (>=0.14.0)
